gitignore_builder/__about__.py
gitignore_builder/__init__.py
gitignore_builder/__main__.py
gitignore_builder/builder.py
gitignore_builder/datamodel.py
gitignore_builder/io_util.py
gitignore_builder/cli/__init__.py
gitignore_builder-1.0.1.dist-info/METADATA
gitignore_builder-1.0.1.dist-info/WHEEL
gitignore_builder-1.0.1.dist-info/entry_points.txt
gitignore_builder-1.0.1.dist-info/licenses/LICENSE.txt
gitignore_builder-1.0.1.dist-info/RECORD
