Metadata-Version: 2.1
Name: gitignore-builder
Version: 1.0.1
Summary: Build the contents of a single .gitignore from several sources.
Project-URL: Documentation, https://github.com/Hrissimir/gitignore-builder#readme
Project-URL: Issues, https://github.com/Hrissimir/gitignore-builder/issues
Project-URL: Source, https://github.com/Hrissimir/gitignore-builder
Author-email: Hrissimir <hrisimir.dakov@gmail.com>
License-File: LICENSE.txt
Classifier: Development Status :: 4 - Beta
Classifier: Programming Language :: Python
Classifier: Programming Language :: Python :: 3.7
Classifier: Programming Language :: Python :: 3.8
Classifier: Programming Language :: Python :: 3.9
Classifier: Programming Language :: Python :: 3.10
Classifier: Programming Language :: Python :: 3.11
Classifier: Programming Language :: Python :: Implementation :: CPython
Classifier: Programming Language :: Python :: Implementation :: PyPy
Requires-Python: >=3.7
Requires-Dist: click
Requires-Dist: platformdirs
Requires-Dist: pyyaml
Requires-Dist: requests
